setup.py
basic_probability/Binomialdistribution.py
basic_probability/Gaussiandistribution.py
basic_probability/Generaldistribution.py
basic_probability/__init__.py
basic_probability.egg-info/PKG-INFO
basic_probability.egg-info/SOURCES.txt
basic_probability.egg-info/dependency_links.txt
basic_probability.egg-info/not-zip-safe
basic_probability.egg-info/top_level.txt