Metadata-Version: 1.0
Name: basic-probability
Version: 0.2
Summary: Library for basic operations on Binomial and Gaussian distributions
Home-page: UNKNOWN
Author: UNKNOWN
Author-email: UNKNOWN
License: UNKNOWN
Platform: UNKNOWN
